wikipedia_content.py
zk_rag_wikipedia-1.1.0.dist-info/METADATA
zk_rag_wikipedia-1.1.0.dist-info/WHEEL
zk_rag_wikipedia-1.1.0.dist-info/entry_points.txt
zk_rag_wikipedia-1.1.0.dist-info/top_level.txt
zk_rag_wikipedia-1.1.0.dist-info/RECORD
