Metadata-Version: 2.2
Name: zk-rag-wikipedia
Version: 1.1.0
Summary: Tool plugin for zk-rag to search Wikipedia
Author-email: Stacey Vetzal <stacey@vetzal.com>
Classifier: Programming Language :: Python :: 3
Classifier: License :: OSI Approved :: MIT License
Classifier: Operating System :: OS Independent
Requires-Python: >=3.11
Requires-Dist: mojentic>=0.2.5
Requires-Dist: wikipedia>=1.4.0
